splitscreen/__init__.py
splitscreen-0.1.2.dist-info/METADATA
splitscreen-0.1.2.dist-info/WHEEL
splitscreen-0.1.2.dist-info/entry_points.txt
splitscreen-0.1.2.dist-info/RECORD
